{"nodes": [{"id": "Jax", "group": 1, "url": "Jax_uvpgkq", "uid": 24}, {"id": "Warwick", "group": 1, "url": "Warwick_pmrx0x", "uid": 19}, {"id": "Xayah", "group": 1, "url": "Xayah_wjn3ve", "uid": 498}, {"id": "Zyra", "group": 1, "url": "Zyra_rhatdv", "uid": 143}, {"id": "Rammus", "group": 1, "url": "Rammus_iahegv", "uid": 33}, {"id": "Illaoi", "group": 1, "url": "Illaoi_bhvo0a", "uid": 420}, {"id": "Corki", "group": 1, "url": "Corki_a8gjdm", "uid": 42}, {"id": "Braum", "group": 1, "url": "Braum_fn5u2s", "uid": 201}, {"id": "Darius", "group": 1, "url": "Darius_sgadhh", "uid": 122}, {"id": "Tryndamere", "group": 1, "url": "Tryndamere_f163dt", "uid": 23}, {"id": "MissFortune", "group": 1, "url": "MissFortune_o7n6az", "uid": 21}, {"id": "Xerath", "group": 1, "url": "Xerath_iky0dg", "uid": 101}, {"id": "Riven", "group": 1, "url": "Riven_k5uhr6", "uid": 92}, {"id": "Orianna", "group": 1, "url": "Orianna_wb9fr0", "uid": 61}, {"id": "Gangplank", "group": 1, "url": "Gangplank_mu92at", "uid": 41}, {"id": "Malphite", "group": 1, "url": "Malphite_opbb29", "uid": 54}, {"id": "Lux", "group": 1, "url": "Lux_pgtgbi", "uid": 99}, {"id": "Shyvana", "group": 1, "url": "Shyvana_ae38l6", "uid": 102}, {"id": "Renekton", "group": 1, "url": "Renekton_ct3fdv", "uid": 58}, {"id": "Fiora", "group": 1, "url": "Fiora_mm5wzj", "uid": 114}, {"id": "Jinx", "group": 1, "url": "Jinx_gfpoju", "uid": 222}, {"id": "Fizz", "group": 1, "url": "Fizz_y6w3ly", "uid": 105}, {"id": "Kassadin", "group": 1, "url": "Kassadin_z31nwe", "uid": 38}, {"id": "Sona", "group": 1, "url": "Sona_wscawa", "uid": 37}, {"id": "Irelia", "group": 1, "url": "Irelia_g95etq", "uid": 39}, {"id": "Rakan", "group": 1, "url": "Rakan_yggftl", "uid": 497}, {"id": "Kindred", "group": 1, "url": "Kindred_iwfh9p", "uid": 203}, {"id": "Cassiopeia", "group": 1, "url": "Cassiopeia_m03xgf", "uid": 69}, {"id": "Maokai", "group": 1, "url": "Maokai_fgqz2s", "uid": 57}, {"id": "Thresh", "group": 1, "url": "Thresh_eowzxf", "uid": 412}, {"id": "Kayle", "group": 1, "url": "Kayle_ite8x6", "uid": 10}, {"id": "Khazix", "group": 1, "url": "Khazix_ornb6c", "uid": 121}, {"id": "Ziggs", "group": 1, "url": "Ziggs_hs36zc", "uid": 115}, {"id": "Syndra", "group": 1, "url": "Syndra_e5x0dw", "uid": 134}, {"id": "Annie", "group": 1, "url": "Annie_vxmi7u", "uid": 1}, {"id": "Yasuo", "group": 1, "url": "Yasuo_fwddlb", "uid": 157}, {"id": "Rengar", "group": 1, "url": "Rengar_pvtzrd", "uid": 107}, {"id": "Ryze", "group": 1, "url": "Ryze_u8qvmi", "uid": 13}, {"id": "Shen", "group": 1, "url": "Shen_oz3nur", "uid": 98}, {"id": "Zac", "group": 1, "url": "Zac_sktndb", "uid": 154}, {"id": "Talon", "group": 1, "url": "Talon_jhv1ip", "uid": 91}, {"id": "Bard", "group": 1, "url": "Bard_dvkodr", "uid": 432}, {"id": "Sion", "group": 1, "url": "Sion_euybyi", "uid": 14}, {"id": "Vayne", "group": 1, "url": "Vayne_citiq9", "uid": 67}, {"id": "Nasus", "group": 1, "url": "Nasus_d8lu6z", "uid": 75}, {"id": "Kayn", "group": 1, "url": "Kayn_yvi1ng", "uid": 141}, {"id": "Chogath", "group": 1, "url": "Chogath_fpaid6", "uid": 31}, {"id": "Lucian", "group": 1, "url": "Lucian_o8ymah", "uid": 236}, {"id": "Leona", "group": 1, "url": "Leona_vtnfcf", "uid": 89}, {"id": "Caitlyn", "group": 1, "url": "Caitlyn_enbgus", "uid": 51}, {"id": "Sejuani", "group": 1, "url": "Sejuani_wgkwz4", "uid": 113}, {"id": "Nocturne", "group": 1, "url": "Nocturne_pmvgif", "uid": 56}, {"id": "Azir", "group": 1, "url": "Azir_irtk6u", "uid": 268}, {"id": "Morgana", "group": 1, "url": "Morgana_i3dlxw", "uid": 25}, {"id": "Teemo", "group": 1, "url": "Teemo_r6iodt", "uid": 17}, {"id": "Urgot", "group": 1, "url": "Urgot_bilkav", "uid": 6}, {"id": "Amumu", "group": 1, "url": "Amumu_euqkbi", "uid": 32}, {"id": "Galio", "group": 1, "url": "Galio_zssmmw", "uid": 3}, {"id": "Heimerdinger", "group": 1, "url": "Heimerdinger_pctrrj", "uid": 74}, {"id": "Ashe", "group": 1, "url": "Ashe_ca5ls0", "uid": 22}, {"id": "Velkoz", "group": 1, "url": "Velkoz_cqmp2m", "uid": 161}, {"id": "Singed", "group": 1, "url": "Singed_qmbcjf", "uid": 27}, {"id": "Varus", "group": 1, "url": "Varus_ixtiwy", "uid": 110}, {"id": "Twitch", "group": 1, "url": "Twitch_do2vya", "uid": 29}, {"id": "Garen", "group": 1, "url": "Garen_kgejh8", "uid": 86}, {"id": "Blitzcrank", "group": 1, "url": "Blitzcrank_wtp21f", "uid": 53}, {"id": "MasterYi", "group": 1, "url": "MasterYi_xbwndn", "uid": 11}, {"id": "Alistar", "group": 1, "url": "Alistar_ndw3sn", "uid": 12}, {"id": "Katarina", "group": 1, "url": "Katarina_u0kdky", "uid": 55}, {"id": "Ekko", "group": 1, "url": "Ekko_aefzsk", "uid": 245}, {"id": "Lulu", "group": 1, "url": "Lulu_hdqisp", "uid": 117}, {"id": "Draven", "group": 1, "url": "Draven_fpcqq3", "uid": 119}, {"id": "Pantheon", "group": 1, "url": "Pantheon_y9ccpv", "uid": 80}, {"id": "XinZhao", "group": 1, "url": "XinZhao_fon5la", "uid": 5}, {"id": "LeeSin", "group": 1, "url": "LeeSin_knukr5", "uid": 64}, {"id": "Taric", "group": 1, "url": "Taric_lh7crm", "uid": 44}, {"id": "Malzahar", "group": 1, "url": "Malzahar_baspfj", "uid": 90}, {"id": "Diana", "group": 1, "url": "Diana_jhvafx", "uid": 131}, {"id": "Tristana", "group": 1, "url": "Tristana_q3a4p1", "uid": 18}, {"id": "Vladimir", "group": 1, "url": "Vladimir_jc1kpf", "uid": 8}, {"id": "JarvanIV", "group": 1, "url": "JarvanIV_zt9yjw", "uid": 59}, {"id": "Nami", "group": 1, "url": "Nami_jz2e7c", "uid": 267}, {"id": "Jhin", "group": 1, "url": "Jhin_z7voxd", "uid": 202}, {"id": "Soraka", "group": 1, "url": "Soraka_fofe4o", "uid": 16}, {"id": "Veigar", "group": 1, "url": "Veigar_ttbsrx", "uid": 45}, {"id": "Janna", "group": 1, "url": "Janna_e9qtxt", "uid": 40}, {"id": "Evelynn", "group": 1, "url": "Evelynn_noivi3", "uid": 28}, {"id": "Gragas", "group": 1, "url": "Gragas_ciptaz", "uid": 79}, {"id": "Zed", "group": 1, "url": "Zed_r2zriz", "uid": 238}, {"id": "Vi", "group": 1, "url": "Vi_km3pjd", "uid": 254}, {"id": "Ahri", "group": 1, "url": "Ahri_j3avlb", "uid": 103}, {"id": "Ezreal", "group": 1, "url": "Ezreal_ejzzsi", "uid": 81}], "links": [{"source_id": 67, "target_id": 40, "source": "Vayne", "target": "Janna", "win": 0.6054216867469879, "value": 332}, {"source_id": 40, "target_id": 67, "source": "Janna", "target": "Vayne", "win": 0.6054216867469879, "value": 332}, {"source_id": 222, "target_id": 40, "source": "Jinx", "target": "Janna", "win": 0.6226415094339622, "value": 212}, {"source_id": 40, "target_id": 222, "source": "Janna", "target": "Jinx", "win": 0.6226415094339622, "value": 212}, {"source_id": 29, "target_id": 59, "source": "Twitch", "target": "JarvanIV", "win": 0.6029411764705882, "value": 204}, {"source_id": 59, "target_id": 29, "source": "JarvanIV", "target": "Twitch", "win": 0.6029411764705882, "value": 204}, {"source_id": 113, "target_id": 18, "source": "Sejuani", "target": "Tristana", "win": 0.6190476190476191, "value": 189}, {"source_id": 18, "target_id": 113, "source": "Tristana", "target": "Sejuani", "win": 0.6190476190476191, "value": 189}, {"source_id": 80, "target_id": 18, "source": "Pantheon", "target": "Tristana", "win": 0.6333333333333333, "value": 180}, {"source_id": 18, "target_id": 80, "source": "Tristana", "target": "Pantheon", "win": 0.6333333333333333, "value": 180}, {"source_id": 157, "target_id": 12, "source": "Yasuo", "target": "Alistar", "win": 0.6012658227848101, "value": 158}, {"source_id": 12, "target_id": 157, "source": "Alistar", "target": "Yasuo", "win": 0.6012658227848101, "value": 158}, {"source_id": 89, "target_id": 51, "source": "Leona", "target": "Caitlyn", "win": 0.6282051282051282, "value": 156}, {"source_id": 51, "target_id": 89, "source": "Caitlyn", "target": "Leona", "win": 0.6282051282051282, "value": 156}, {"source_id": 67, "target_id": 113, "source": "Vayne", "target": "Sejuani", "win": 0.6428571428571429, "value": 154}, {"source_id": 113, "target_id": 67, "source": "Sejuani", "target": "Vayne", "win": 0.6428571428571429, "value": 154}, {"source_id": 51, "target_id": 86, "source": "Caitlyn", "target": "Garen", "win": 0.609271523178808, "value": 151}, {"source_id": 86, "target_id": 51, "source": "Garen", "target": "Caitlyn", "win": 0.609271523178808, "value": 151}, {"source_id": 57, "target_id": 67, "source": "Maokai", "target": "Vayne", "win": 0.6111111111111112, "value": 144}, {"source_id": 67, "target_id": 57, "source": "Vayne", "target": "Maokai", "win": 0.6111111111111112, "value": 144}, {"source_id": 25, "target_id": 103, "source": "Morgana", "target": "Ahri", "win": 0.6153846153846154, "value": 143}, {"source_id": 103, "target_id": 25, "source": "Ahri", "target": "Morgana", "win": 0.6153846153846154, "value": 143}, {"source_id": 236, "target_id": 11, "source": "Lucian", "target": "MasterYi", "win": 0.6028368794326241, "value": 141}, {"source_id": 11, "target_id": 236, "source": "MasterYi", "target": "Lucian", "win": 0.6028368794326241, "value": 141}, {"source_id": 21, "target_id": 238, "source": "MissFortune", "target": "Zed", "win": 0.6029411764705882, "value": 136}, {"source_id": 141, "target_id": 89, "source": "Kayn", "target": "Leona", "win": 0.6617647058823529, "value": 136}, {"source_id": 89, "target_id": 141, "source": "Leona", "target": "Kayn", "win": 0.6617647058823529, "value": 136}, {"source_id": 238, "target_id": 21, "source": "Zed", "target": "MissFortune", "win": 0.6029411764705882, "value": 136}, {"source_id": 498, "target_id": 86, "source": "Xayah", "target": "Garen", "win": 0.6299212598425197, "value": 127}, {"source_id": 222, "target_id": 121, "source": "Jinx", "target": "Khazix", "win": 0.6377952755905512, "value": 127}, {"source_id": 121, "target_id": 222, "source": "Khazix", "target": "Jinx", "win": 0.6377952755905512, "value": 127}, {"source_id": 86, "target_id": 498, "source": "Garen", "target": "Xayah", "win": 0.6299212598425197, "value": 127}, {"source_id": 86, "target_id": 45, "source": "Garen", "target": "Veigar", "win": 0.6220472440944882, "value": 127}, {"source_id": 45, "target_id": 86, "source": "Veigar", "target": "Garen", "win": 0.6220472440944882, "value": 127}, {"source_id": 21, "target_id": 86, "source": "MissFortune", "target": "Garen", "win": 0.6111111111111112, "value": 126}, {"source_id": 86, "target_id": 21, "source": "Garen", "target": "MissFortune", "win": 0.6111111111111112, "value": 126}, {"source_id": 86, "target_id": 16, "source": "Garen", "target": "Soraka", "win": 0.6422764227642277, "value": 123}, {"source_id": 16, "target_id": 86, "source": "Soraka", "target": "Garen", "win": 0.6422764227642277, "value": 123}, {"source_id": 24, "target_id": 103, "source": "Jax", "target": "Ahri", "win": 0.6033057851239669, "value": 121}, {"source_id": 103, "target_id": 24, "source": "Ahri", "target": "Jax", "win": 0.6033057851239669, "value": 121}, {"source_id": 67, "target_id": 254, "source": "Vayne", "target": "Vi", "win": 0.6101694915254238, "value": 118}, {"source_id": 53, "target_id": 245, "source": "Blitzcrank", "target": "Ekko", "win": 0.6016949152542372, "value": 118}, {"source_id": 245, "target_id": 53, "source": "Ekko", "target": "Blitzcrank", "win": 0.6016949152542372, "value": 118}, {"source_id": 254, "target_id": 67, "source": "Vi", "target": "Vayne", "win": 0.6101694915254238, "value": 118}, {"source_id": 99, "target_id": 59, "source": "Lux", "target": "JarvanIV", "win": 0.6068376068376068, "value": 117}, {"source_id": 37, "target_id": 51, "source": "Sona", "target": "Caitlyn", "win": 0.6153846153846154, "value": 117}, {"source_id": 51, "target_id": 37, "source": "Caitlyn", "target": "Sona", "win": 0.6153846153846154, "value": 117}, {"source_id": 59, "target_id": 99, "source": "JarvanIV", "target": "Lux", "win": 0.6068376068376068, "value": 117}, {"source_id": 117, "target_id": 45, "source": "Lulu", "target": "Veigar", "win": 0.7130434782608696, "value": 115}, {"source_id": 45, "target_id": 117, "source": "Veigar", "target": "Lulu", "win": 0.7130434782608696, "value": 115}, {"source_id": 44, "target_id": 81, "source": "Taric", "target": "Ezreal", "win": 0.6754385964912281, "value": 114}, {"source_id": 81, "target_id": 44, "source": "Ezreal", "target": "Taric", "win": 0.6754385964912281, "value": 114}, {"source_id": 53, "target_id": 59, "source": "Blitzcrank", "target": "JarvanIV", "win": 0.6371681415929203, "value": 113}, {"source_id": 59, "target_id": 53, "source": "JarvanIV", "target": "Blitzcrank", "win": 0.6371681415929203, "value": 113}, {"source_id": 21, "target_id": 17, "source": "MissFortune", "target": "Teemo", "win": 0.6428571428571429, "value": 112}, {"source_id": 17, "target_id": 21, "source": "Teemo", "target": "MissFortune", "win": 0.6428571428571429, "value": 112}, {"source_id": 53, "target_id": 119, "source": "Blitzcrank", "target": "Draven", "win": 0.6160714285714286, "value": 112}, {"source_id": 119, "target_id": 53, "source": "Draven", "target": "Blitzcrank", "win": 0.6160714285714286, "value": 112}, {"source_id": 19, "target_id": 45, "source": "Warwick", "target": "Veigar", "win": 0.6190476190476191, "value": 105}, {"source_id": 498, "target_id": 5, "source": "Xayah", "target": "XinZhao", "win": 0.6190476190476191, "value": 105}, {"source_id": 99, "target_id": 89, "source": "Lux", "target": "Leona", "win": 0.638095238095238, "value": 105}, {"source_id": 89, "target_id": 99, "source": "Leona", "target": "Lux", "win": 0.638095238095238, "value": 105}, {"source_id": 5, "target_id": 498, "source": "XinZhao", "target": "Xayah", "win": 0.6190476190476191, "value": 105}, {"source_id": 45, "target_id": 19, "source": "Veigar", "target": "Warwick", "win": 0.6190476190476191, "value": 105}, {"source_id": 117, "target_id": 103, "source": "Lulu", "target": "Ahri", "win": 0.625, "value": 104}, {"source_id": 103, "target_id": 117, "source": "Ahri", "target": "Lulu", "win": 0.625, "value": 104}, {"source_id": 51, "target_id": 5, "source": "Caitlyn", "target": "XinZhao", "win": 0.6176470588235294, "value": 102}, {"source_id": 5, "target_id": 51, "source": "XinZhao", "target": "Caitlyn", "win": 0.6176470588235294, "value": 102}, {"source_id": 24, "target_id": 17, "source": "Jax", "target": "Teemo", "win": 0.63, "value": 100}, {"source_id": 92, "target_id": 45, "source": "Riven", "target": "Veigar", "win": 0.68, "value": 100}, {"source_id": 17, "target_id": 24, "source": "Teemo", "target": "Jax", "win": 0.63, "value": 100}, {"source_id": 45, "target_id": 92, "source": "Veigar", "target": "Riven", "win": 0.68, "value": 100}, {"source_id": 122, "target_id": 412, "source": "Darius", "target": "Thresh", "win": 0.6020408163265306, "value": 98}, {"source_id": 412, "target_id": 122, "source": "Thresh", "target": "Darius", "win": 0.6020408163265306, "value": 98}, {"source_id": 222, "target_id": 254, "source": "Jinx", "target": "Vi", "win": 0.6494845360824743, "value": 97}, {"source_id": 157, "target_id": 86, "source": "Yasuo", "target": "Garen", "win": 0.6597938144329897, "value": 97}, {"source_id": 86, "target_id": 157, "source": "Garen", "target": "Yasuo", "win": 0.6597938144329897, "value": 97}, {"source_id": 254, "target_id": 222, "source": "Vi", "target": "Jinx", "win": 0.6494845360824743, "value": 97}, {"source_id": 21, "target_id": 105, "source": "MissFortune", "target": "Fizz", "win": 0.6105263157894737, "value": 95}, {"source_id": 105, "target_id": 21, "source": "Fizz", "target": "MissFortune", "win": 0.6105263157894737, "value": 95}, {"source_id": 21, "target_id": 90, "source": "MissFortune", "target": "Malzahar", "win": 0.6021505376344086, "value": 93}, {"source_id": 121, "target_id": 45, "source": "Khazix", "target": "Veigar", "win": 0.6021505376344086, "value": 93}, {"source_id": 245, "target_id": 16, "source": "Ekko", "target": "Soraka", "win": 0.6344086021505376, "value": 93}, {"source_id": 90, "target_id": 21, "source": "Malzahar", "target": "MissFortune", "win": 0.6021505376344086, "value": 93}, {"source_id": 16, "target_id": 245, "source": "Soraka", "target": "Ekko", "win": 0.6344086021505376, "value": 93}, {"source_id": 45, "target_id": 121, "source": "Veigar", "target": "Khazix", "win": 0.6021505376344086, "value": 93}, {"source_id": 89, "target_id": 80, "source": "Leona", "target": "Pantheon", "win": 0.6413043478260869, "value": 92}, {"source_id": 89, "target_id": 45, "source": "Leona", "target": "Veigar", "win": 0.6304347826086957, "value": 92}, {"source_id": 80, "target_id": 89, "source": "Pantheon", "target": "Leona", "win": 0.6413043478260869, "value": 92}, {"source_id": 45, "target_id": 89, "source": "Veigar", "target": "Leona", "win": 0.6304347826086957, "value": 92}, {"source_id": 21, "target_id": 121, "source": "MissFortune", "target": "Khazix", "win": 0.6777777777777778, "value": 90}, {"source_id": 121, "target_id": 21, "source": "Khazix", "target": "MissFortune", "win": 0.6777777777777778, "value": 90}, {"source_id": 19, "target_id": 86, "source": "Warwick", "target": "Garen", "win": 0.6136363636363636, "value": 88}, {"source_id": 21, "target_id": 75, "source": "MissFortune", "target": "Nasus", "win": 0.6136363636363636, "value": 88}, {"source_id": 92, "target_id": 497, "source": "Riven", "target": "Rakan", "win": 0.6363636363636364, "value": 88}, {"source_id": 92, "target_id": 110, "source": "Riven", "target": "Varus", "win": 0.6022727272727273, "value": 88}, {"source_id": 497, "target_id": 92, "source": "Rakan", "target": "Riven", "win": 0.6363636363636364, "value": 88}, {"source_id": 497, "target_id": 28, "source": "Rakan", "target": "Evelynn", "win": 0.6022727272727273, "value": 88}, {"source_id": 75, "target_id": 21, "source": "Nasus", "target": "MissFortune", "win": 0.6136363636363636, "value": 88}, {"source_id": 110, "target_id": 92, "source": "Varus", "target": "Riven", "win": 0.6022727272727273, "value": 88}, {"source_id": 86, "target_id": 19, "source": "Garen", "target": "Warwick", "win": 0.6136363636363636, "value": 88}, {"source_id": 28, "target_id": 497, "source": "Evelynn", "target": "Rakan", "win": 0.6022727272727273, "value": 88}, {"source_id": 105, "target_id": 75, "source": "Fizz", "target": "Nasus", "win": 0.627906976744186, "value": 86}, {"source_id": 75, "target_id": 105, "source": "Nasus", "target": "Fizz", "win": 0.627906976744186, "value": 86}, {"source_id": 69, "target_id": 67, "source": "Cassiopeia", "target": "Vayne", "win": 0.6190476190476191, "value": 84}, {"source_id": 432, "target_id": 29, "source": "Bard", "target": "Twitch", "win": 0.6071428571428571, "value": 84}, {"source_id": 67, "target_id": 69, "source": "Vayne", "target": "Cassiopeia", "win": 0.6190476190476191, "value": 84}, {"source_id": 29, "target_id": 432, "source": "Twitch", "target": "Bard", "win": 0.6071428571428571, "value": 84}, {"source_id": 24, "target_id": 1, "source": "Jax", "target": "Annie", "win": 0.6024096385542169, "value": 83}, {"source_id": 498, "target_id": 98, "source": "Xayah", "target": "Shen", "win": 0.6024096385542169, "value": 83}, {"source_id": 41, "target_id": 40, "source": "Gangplank", "target": "Janna", "win": 0.6506024096385542, "value": 83}, {"source_id": 105, "target_id": 40, "source": "Fizz", "target": "Janna", "win": 0.6144578313253012, "value": 83}, {"source_id": 1, "target_id": 24, "source": "Annie", "target": "Jax", "win": 0.6024096385542169, "value": 83}, {"source_id": 98, "target_id": 498, "source": "Shen", "target": "Xayah", "win": 0.6024096385542169, "value": 83}, {"source_id": 40, "target_id": 41, "source": "Janna", "target": "Gangplank", "win": 0.6506024096385542, "value": 83}, {"source_id": 40, "target_id": 105, "source": "Janna", "target": "Fizz", "win": 0.6144578313253012, "value": 83}, {"source_id": 23, "target_id": 21, "source": "Tryndamere", "target": "MissFortune", "win": 0.6097560975609756, "value": 82}, {"source_id": 21, "target_id": 23, "source": "MissFortune", "target": "Tryndamere", "win": 0.6097560975609756, "value": 82}, {"source_id": 23, "target_id": 22, "source": "Tryndamere", "target": "Ashe", "win": 0.6049382716049383, "value": 81}, {"source_id": 412, "target_id": 1, "source": "Thresh", "target": "Annie", "win": 0.6790123456790124, "value": 81}, {"source_id": 1, "target_id": 412, "source": "Annie", "target": "Thresh", "win": 0.6790123456790124, "value": 81}, {"source_id": 89, "target_id": 8, "source": "Leona", "target": "Vladimir", "win": 0.6296296296296297, "value": 81}, {"source_id": 22, "target_id": 23, "source": "Ashe", "target": "Tryndamere", "win": 0.6049382716049383, "value": 81}, {"source_id": 8, "target_id": 89, "source": "Vladimir", "target": "Leona", "win": 0.6296296296296297, "value": 81}, {"source_id": 119, "target_id": 59, "source": "Draven", "target": "JarvanIV", "win": 0.6125, "value": 80}, {"source_id": 59, "target_id": 119, "source": "JarvanIV", "target": "Draven", "win": 0.6125, "value": 80}, {"source_id": 19, "target_id": 75, "source": "Warwick", "target": "Nasus", "win": 0.6075949367088608, "value": 79}, {"source_id": 497, "target_id": 3, "source": "Rakan", "target": "Galio", "win": 0.6075949367088608, "value": 79}, {"source_id": 75, "target_id": 19, "source": "Nasus", "target": "Warwick", "win": 0.6075949367088608, "value": 79}, {"source_id": 3, "target_id": 497, "source": "Galio", "target": "Rakan", "win": 0.6075949367088608, "value": 79}, {"source_id": 91, "target_id": 53, "source": "Talon", "target": "Blitzcrank", "win": 0.6233766233766234, "value": 77}, {"source_id": 53, "target_id": 91, "source": "Blitzcrank", "target": "Talon", "win": 0.6233766233766234, "value": 77}, {"source_id": 54, "target_id": 222, "source": "Malphite", "target": "Jinx", "win": 0.6052631578947368, "value": 76}, {"source_id": 222, "target_id": 54, "source": "Jinx", "target": "Malphite", "win": 0.6052631578947368, "value": 76}, {"source_id": 121, "target_id": 75, "source": "Khazix", "target": "Nasus", "win": 0.6533333333333333, "value": 75}, {"source_id": 75, "target_id": 121, "source": "Nasus", "target": "Khazix", "win": 0.6533333333333333, "value": 75}, {"source_id": 17, "target_id": 103, "source": "Teemo", "target": "Ahri", "win": 0.6133333333333333, "value": 75}, {"source_id": 27, "target_id": 64, "source": "Singed", "target": "LeeSin", "win": 0.6933333333333334, "value": 75}, {"source_id": 64, "target_id": 27, "source": "LeeSin", "target": "Singed", "win": 0.6933333333333334, "value": 75}, {"source_id": 103, "target_id": 17, "source": "Ahri", "target": "Teemo", "win": 0.6133333333333333, "value": 75}, {"source_id": 236, "target_id": 59, "source": "Lucian", "target": "JarvanIV", "win": 0.6081081081081081, "value": 74}, {"source_id": 59, "target_id": 236, "source": "JarvanIV", "target": "Lucian", "win": 0.6081081081081081, "value": 74}, {"source_id": 222, "target_id": 6, "source": "Jinx", "target": "Urgot", "win": 0.684931506849315, "value": 73}, {"source_id": 37, "target_id": 45, "source": "Sona", "target": "Veigar", "win": 0.6575342465753424, "value": 73}, {"source_id": 6, "target_id": 222, "source": "Urgot", "target": "Jinx", "win": 0.684931506849315, "value": 73}, {"source_id": 74, "target_id": 18, "source": "Heimerdinger", "target": "Tristana", "win": 0.6164383561643836, "value": 73}, {"source_id": 18, "target_id": 74, "source": "Tristana", "target": "Heimerdinger", "win": 0.6164383561643836, "value": 73}, {"source_id": 45, "target_id": 37, "source": "Veigar", "target": "Sona", "win": 0.6575342465753424, "value": 73}, {"source_id": 157, "target_id": 154, "source": "Yasuo", "target": "Zac", "win": 0.6056338028169014, "value": 71}, {"source_id": 154, "target_id": 157, "source": "Zac", "target": "Yasuo", "win": 0.6056338028169014, "value": 71}, {"source_id": 75, "target_id": 16, "source": "Nasus", "target": "Soraka", "win": 0.6056338028169014, "value": 71}, {"source_id": 17, "target_id": 40, "source": "Teemo", "target": "Janna", "win": 0.6056338028169014, "value": 71}, {"source_id": 16, "target_id": 75, "source": "Soraka", "target": "Nasus", "win": 0.6056338028169014, "value": 71}, {"source_id": 40, "target_id": 17, "source": "Janna", "target": "Teemo", "win": 0.6056338028169014, "value": 71}, {"source_id": 498, "target_id": 27, "source": "Xayah", "target": "Singed", "win": 0.6142857142857143, "value": 70}, {"source_id": 115, "target_id": 67, "source": "Ziggs", "target": "Vayne", "win": 0.6285714285714286, "value": 70}, {"source_id": 67, "target_id": 115, "source": "Vayne", "target": "Ziggs", "win": 0.6285714285714286, "value": 70}, {"source_id": 27, "target_id": 498, "source": "Singed", "target": "Xayah", "win": 0.6142857142857143, "value": 70}, {"source_id": 498, "target_id": 32, "source": "Xayah", "target": "Amumu", "win": 0.6376811594202898, "value": 69}, {"source_id": 21, "target_id": 1, "source": "MissFortune", "target": "Annie", "win": 0.6376811594202898, "value": 69}, {"source_id": 1, "target_id": 21, "source": "Annie", "target": "MissFortune", "win": 0.6376811594202898, "value": 69}, {"source_id": 32, "target_id": 498, "source": "Amumu", "target": "Xayah", "win": 0.6376811594202898, "value": 69}, {"source_id": 24, "target_id": 91, "source": "Jax", "target": "Talon", "win": 0.6029411764705882, "value": 68}, {"source_id": 61, "target_id": 113, "source": "Orianna", "target": "Sejuani", "win": 0.6029411764705882, "value": 68}, {"source_id": 91, "target_id": 24, "source": "Talon", "target": "Jax", "win": 0.6029411764705882, "value": 68}, {"source_id": 113, "target_id": 61, "source": "Sejuani", "target": "Orianna", "win": 0.6029411764705882, "value": 68}, {"source_id": 61, "target_id": 202, "source": "Orianna", "target": "Jhin", "win": 0.6119402985074627, "value": 67}, {"source_id": 202, "target_id": 61, "source": "Jhin", "target": "Orianna", "win": 0.6119402985074627, "value": 67}, {"source_id": 420, "target_id": 222, "source": "Illaoi", "target": "Jinx", "win": 0.7727272727272727, "value": 66}, {"source_id": 61, "target_id": 5, "source": "Orianna", "target": "XinZhao", "win": 0.6515151515151515, "value": 66}, {"source_id": 222, "target_id": 420, "source": "Jinx", "target": "Illaoi", "win": 0.7727272727272727, "value": 66}, {"source_id": 37, "target_id": 17, "source": "Sona", "target": "Teemo", "win": 0.6515151515151515, "value": 66}, {"source_id": 57, "target_id": 110, "source": "Maokai", "target": "Varus", "win": 0.6212121212121212, "value": 66}, {"source_id": 154, "target_id": 18, "source": "Zac", "target": "Tristana", "win": 0.6060606060606061, "value": 66}, {"source_id": 17, "target_id": 37, "source": "Teemo", "target": "Sona", "win": 0.6515151515151515, "value": 66}, {"source_id": 110, "target_id": 57, "source": "Varus", "target": "Maokai", "win": 0.6212121212121212, "value": 66}, {"source_id": 53, "target_id": 90, "source": "Blitzcrank", "target": "Malzahar", "win": 0.6363636363636364, "value": 66}, {"source_id": 5, "target_id": 61, "source": "XinZhao", "target": "Orianna", "win": 0.6515151515151515, "value": 66}, {"source_id": 90, "target_id": 53, "source": "Malzahar", "target": "Blitzcrank", "win": 0.6363636363636364, "value": 66}, {"source_id": 18, "target_id": 154, "source": "Tristana", "target": "Zac", "win": 0.6060606060606061, "value": 66}, {"source_id": 40, "target_id": 254, "source": "Janna", "target": "Vi", "win": 0.6060606060606061, "value": 66}, {"source_id": 254, "target_id": 40, "source": "Vi", "target": "Janna", "win": 0.6060606060606061, "value": 66}, {"source_id": 498, "target_id": 1, "source": "Xayah", "target": "Annie", "win": 0.7538461538461538, "value": 65}, {"source_id": 1, "target_id": 498, "source": "Annie", "target": "Xayah", "win": 0.7538461538461538, "value": 65}, {"source_id": 19, "target_id": 17, "source": "Warwick", "target": "Teemo", "win": 0.640625, "value": 64}, {"source_id": 122, "target_id": 157, "source": "Darius", "target": "Yasuo", "win": 0.609375, "value": 64}, {"source_id": 41, "target_id": 89, "source": "Gangplank", "target": "Leona", "win": 0.6875, "value": 64}, {"source_id": 105, "target_id": 110, "source": "Fizz", "target": "Varus", "win": 0.609375, "value": 64}, {"source_id": 157, "target_id": 122, "source": "Yasuo", "target": "Darius", "win": 0.609375, "value": 64}, {"source_id": 432, "target_id": 59, "source": "Bard", "target": "JarvanIV", "win": 0.640625, "value": 64}, {"source_id": 89, "target_id": 41, "source": "Leona", "target": "Gangplank", "win": 0.6875, "value": 64}, {"source_id": 17, "target_id": 19, "source": "Teemo", "target": "Warwick", "win": 0.640625, "value": 64}, {"source_id": 110, "target_id": 105, "source": "Varus", "target": "Fizz", "win": 0.609375, "value": 64}, {"source_id": 86, "target_id": 59, "source": "Garen", "target": "JarvanIV", "win": 0.609375, "value": 64}, {"source_id": 5, "target_id": 103, "source": "XinZhao", "target": "Ahri", "win": 0.640625, "value": 64}, {"source_id": 90, "target_id": 16, "source": "Malzahar", "target": "Soraka", "win": 0.671875, "value": 64}, {"source_id": 59, "target_id": 432, "source": "JarvanIV", "target": "Bard", "win": 0.640625, "value": 64}, {"source_id": 59, "target_id": 86, "source": "JarvanIV", "target": "Garen", "win": 0.609375, "value": 64}, {"source_id": 16, "target_id": 90, "source": "Soraka", "target": "Malzahar", "win": 0.671875, "value": 64}, {"source_id": 103, "target_id": 5, "source": "Ahri", "target": "XinZhao", "win": 0.640625, "value": 64}, {"source_id": 91, "target_id": 119, "source": "Talon", "target": "Draven", "win": 0.6190476190476191, "value": 63}, {"source_id": 161, "target_id": 18, "source": "Velkoz", "target": "Tristana", "win": 0.6507936507936508, "value": 63}, {"source_id": 119, "target_id": 91, "source": "Draven", "target": "Talon", "win": 0.6190476190476191, "value": 63}, {"source_id": 18, "target_id": 161, "source": "Tristana", "target": "Velkoz", "win": 0.6507936507936508, "value": 63}, {"source_id": 54, "target_id": 53, "source": "Malphite", "target": "Blitzcrank", "win": 0.6451612903225806, "value": 62}, {"source_id": 86, "target_id": 131, "source": "Garen", "target": "Diana", "win": 0.6290322580645161, "value": 62}, {"source_id": 53, "target_id": 54, "source": "Blitzcrank", "target": "Malphite", "win": 0.6451612903225806, "value": 62}, {"source_id": 131, "target_id": 86, "source": "Diana", "target": "Garen", "win": 0.6290322580645161, "value": 62}, {"source_id": 69, "target_id": 64, "source": "Cassiopeia", "target": "LeeSin", "win": 0.6065573770491803, "value": 61}, {"source_id": 57, "target_id": 267, "source": "Maokai", "target": "Nami", "win": 0.6065573770491803, "value": 61}, {"source_id": 121, "target_id": 17, "source": "Khazix", "target": "Teemo", "win": 0.6721311475409836, "value": 61}, {"source_id": 17, "target_id": 121, "source": "Teemo", "target": "Khazix", "win": 0.6721311475409836, "value": 61}, {"source_id": 64, "target_id": 69, "source": "LeeSin", "target": "Cassiopeia", "win": 0.6065573770491803, "value": 61}, {"source_id": 267, "target_id": 57, "source": "Nami", "target": "Maokai", "win": 0.6065573770491803, "value": 61}, {"source_id": 19, "target_id": 119, "source": "Warwick", "target": "Draven", "win": 0.6333333333333333, "value": 60}, {"source_id": 37, "target_id": 28, "source": "Sona", "target": "Evelynn", "win": 0.6333333333333333, "value": 60}, {"source_id": 497, "target_id": 75, "source": "Rakan", "target": "Nasus", "win": 0.6333333333333333, "value": 60}, {"source_id": 1, "target_id": 86, "source": "Annie", "target": "Garen", "win": 0.6166666666666667, "value": 60}, {"source_id": 75, "target_id": 497, "source": "Nasus", "target": "Rakan", "win": 0.6333333333333333, "value": 60}, {"source_id": 89, "target_id": 3, "source": "Leona", "target": "Galio", "win": 0.6666666666666666, "value": 60}, {"source_id": 3, "target_id": 89, "source": "Galio", "target": "Leona", "win": 0.6666666666666666, "value": 60}, {"source_id": 3, "target_id": 53, "source": "Galio", "target": "Blitzcrank", "win": 0.7166666666666667, "value": 60}, {"source_id": 86, "target_id": 1, "source": "Garen", "target": "Annie", "win": 0.6166666666666667, "value": 60}, {"source_id": 53, "target_id": 3, "source": "Blitzcrank", "target": "Galio", "win": 0.7166666666666667, "value": 60}, {"source_id": 55, "target_id": 80, "source": "Katarina", "target": "Pantheon", "win": 0.6166666666666667, "value": 60}, {"source_id": 119, "target_id": 19, "source": "Draven", "target": "Warwick", "win": 0.6333333333333333, "value": 60}, {"source_id": 80, "target_id": 55, "source": "Pantheon", "target": "Katarina", "win": 0.6166666666666667, "value": 60}, {"source_id": 28, "target_id": 37, "source": "Evelynn", "target": "Sona", "win": 0.6333333333333333, "value": 60}, {"source_id": 102, "target_id": 238, "source": "Shyvana", "target": "Zed", "win": 0.6101694915254238, "value": 59}, {"source_id": 58, "target_id": 53, "source": "Renekton", "target": "Blitzcrank", "win": 0.6440677966101694, "value": 59}, {"source_id": 37, "target_id": 59, "source": "Sona", "target": "JarvanIV", "win": 0.7288135593220338, "value": 59}, {"source_id": 57, "target_id": 11, "source": "Maokai", "target": "MasterYi", "win": 0.6101694915254238, "value": 59}, {"source_id": 13, "target_id": 59, "source": "Ryze", "target": "JarvanIV", "win": 0.6610169491525424, "value": 59}, {"source_id": 89, "target_id": 254, "source": "Leona", "target": "Vi", "win": 0.6101694915254238, "value": 59}, {"source_id": 51, "target_id": 131, "source": "Caitlyn", "target": "Diana", "win": 0.6101694915254238, "value": 59}, {"source_id": 6, "target_id": 45, "source": "Urgot", "target": "Veigar", "win": 0.6610169491525424, "value": 59}, {"source_id": 53, "target_id": 58, "source": "Blitzcrank", "target": "Renekton", "win": 0.6440677966101694, "value": 59}, {"source_id": 11, "target_id": 57, "source": "MasterYi", "target": "Maokai", "win": 0.6101694915254238, "value": 59}, {"source_id": 55, "target_id": 79, "source": "Katarina", "target": "Gragas", "win": 0.6101694915254238, "value": 59}, {"source_id": 131, "target_id": 51, "source": "Diana", "target": "Caitlyn", "win": 0.6101694915254238, "value": 59}, {"source_id": 59, "target_id": 37, "source": "JarvanIV", "target": "Sona", "win": 0.7288135593220338, "value": 59}, {"source_id": 59, "target_id": 13, "source": "JarvanIV", "target": "Ryze", "win": 0.6610169491525424, "value": 59}, {"source_id": 45, "target_id": 6, "source": "Veigar", "target": "Urgot", "win": 0.6610169491525424, "value": 59}, {"source_id": 79, "target_id": 55, "source": "Gragas", "target": "Katarina", "win": 0.6101694915254238, "value": 59}, {"source_id": 238, "target_id": 102, "source": "Zed", "target": "Shyvana", "win": 0.6101694915254238, "value": 59}, {"source_id": 254, "target_id": 89, "source": "Vi", "target": "Leona", "win": 0.6101694915254238, "value": 59}, {"source_id": 24, "target_id": 114, "source": "Jax", "target": "Fiora", "win": 0.6551724137931034, "value": 58}, {"source_id": 19, "target_id": 497, "source": "Warwick", "target": "Rakan", "win": 0.6379310344827587, "value": 58}, {"source_id": 19, "target_id": 134, "source": "Warwick", "target": "Syndra", "win": 0.6206896551724138, "value": 58}, {"source_id": 33, "target_id": 222, "source": "Rammus", "target": "Jinx", "win": 0.7241379310344828, "value": 58}, {"source_id": 101, "target_id": 64, "source": "Xerath", "target": "LeeSin", "win": 0.6379310344827587, "value": 58}, {"source_id": 114, "target_id": 24, "source": "Fiora", "target": "Jax", "win": 0.6551724137931034, "value": 58}, {"source_id": 222, "target_id": 33, "source": "Jinx", "target": "Rammus", "win": 0.7241379310344828, "value": 58}, {"source_id": 497, "target_id": 19, "source": "Rakan", "target": "Warwick", "win": 0.6379310344827587, "value": 58}, {"source_id": 497, "target_id": 80, "source": "Rakan", "target": "Pantheon", "win": 0.6379310344827587, "value": 58}, {"source_id": 203, "target_id": 67, "source": "Kindred", "target": "Vayne", "win": 0.6551724137931034, "value": 58}, {"source_id": 121, "target_id": 8, "source": "Khazix", "target": "Vladimir", "win": 0.6379310344827587, "value": 58}, {"source_id": 134, "target_id": 19, "source": "Syndra", "target": "Warwick", "win": 0.6206896551724138, "value": 58}, {"source_id": 67, "target_id": 203, "source": "Vayne", "target": "Kindred", "win": 0.6551724137931034, "value": 58}, {"source_id": 31, "target_id": 103, "source": "Chogath", "target": "Ahri", "win": 0.6551724137931034, "value": 58}, {"source_id": 53, "target_id": 131, "source": "Blitzcrank", "target": "Diana", "win": 0.6379310344827587, "value": 58}, {"source_id": 80, "target_id": 497, "source": "Pantheon", "target": "Rakan", "win": 0.6379310344827587, "value": 58}, {"source_id": 80, "target_id": 40, "source": "Pantheon", "target": "Janna", "win": 0.6551724137931034, "value": 58}, {"source_id": 64, "target_id": 101, "source": "LeeSin", "target": "Xerath", "win": 0.6379310344827587, "value": 58}, {"source_id": 131, "target_id": 53, "source": "Diana", "target": "Blitzcrank", "win": 0.6379310344827587, "value": 58}, {"source_id": 8, "target_id": 121, "source": "Vladimir", "target": "Khazix", "win": 0.6379310344827587, "value": 58}, {"source_id": 202, "target_id": 16, "source": "Jhin", "target": "Soraka", "win": 0.6551724137931034, "value": 58}, {"source_id": 16, "target_id": 202, "source": "Soraka", "target": "Jhin", "win": 0.6551724137931034, "value": 58}, {"source_id": 40, "target_id": 80, "source": "Janna", "target": "Pantheon", "win": 0.6551724137931034, "value": 58}, {"source_id": 103, "target_id": 31, "source": "Ahri", "target": "Chogath", "win": 0.6551724137931034, "value": 58}, {"source_id": 122, "target_id": 238, "source": "Darius", "target": "Zed", "win": 0.6140350877192983, "value": 57}, {"source_id": 23, "target_id": 61, "source": "Tryndamere", "target": "Orianna", "win": 0.631578947368421, "value": 57}, {"source_id": 61, "target_id": 23, "source": "Orianna", "target": "Tryndamere", "win": 0.631578947368421, "value": 57}, {"source_id": 105, "target_id": 98, "source": "Fizz", "target": "Shen", "win": 0.6140350877192983, "value": 57}, {"source_id": 98, "target_id": 105, "source": "Shen", "target": "Fizz", "win": 0.6140350877192983, "value": 57}, {"source_id": 31, "target_id": 267, "source": "Chogath", "target": "Nami", "win": 0.6140350877192983, "value": 57}, {"source_id": 56, "target_id": 18, "source": "Nocturne", "target": "Tristana", "win": 0.6140350877192983, "value": 57}, {"source_id": 64, "target_id": 131, "source": "LeeSin", "target": "Diana", "win": 0.6842105263157895, "value": 57}, {"source_id": 131, "target_id": 64, "source": "Diana", "target": "LeeSin", "win": 0.6842105263157895, "value": 57}, {"source_id": 18, "target_id": 56, "source": "Tristana", "target": "Nocturne", "win": 0.6140350877192983, "value": 57}, {"source_id": 267, "target_id": 31, "source": "Nami", "target": "Chogath", "win": 0.6140350877192983, "value": 57}, {"source_id": 238, "target_id": 122, "source": "Zed", "target": "Darius", "win": 0.6140350877192983, "value": 57}, {"source_id": 122, "target_id": 119, "source": "Darius", "target": "Draven", "win": 0.6071428571428571, "value": 56}, {"source_id": 119, "target_id": 122, "source": "Draven", "target": "Darius", "win": 0.6071428571428571, "value": 56}, {"source_id": 222, "target_id": 38, "source": "Jinx", "target": "Kassadin", "win": 0.6363636363636364, "value": 55}, {"source_id": 38, "target_id": 222, "source": "Kassadin", "target": "Jinx", "win": 0.6363636363636364, "value": 55}, {"source_id": 115, "target_id": 64, "source": "Ziggs", "target": "LeeSin", "win": 0.6363636363636364, "value": 55}, {"source_id": 6, "target_id": 103, "source": "Urgot", "target": "Ahri", "win": 0.6181818181818182, "value": 55}, {"source_id": 64, "target_id": 115, "source": "LeeSin", "target": "Ziggs", "win": 0.6363636363636364, "value": 55}, {"source_id": 103, "target_id": 6, "source": "Ahri", "target": "Urgot", "win": 0.6181818181818182, "value": 55}, {"source_id": 19, "target_id": 267, "source": "Warwick", "target": "Nami", "win": 0.6296296296296297, "value": 54}, {"source_id": 101, "target_id": 18, "source": "Xerath", "target": "Tristana", "win": 0.6296296296296297, "value": 54}, {"source_id": 39, "target_id": 117, "source": "Irelia", "target": "Lulu", "win": 0.6296296296296297, "value": 54}, {"source_id": 117, "target_id": 39, "source": "Lulu", "target": "Irelia", "win": 0.6296296296296297, "value": 54}, {"source_id": 18, "target_id": 101, "source": "Tristana", "target": "Xerath", "win": 0.6296296296296297, "value": 54}, {"source_id": 267, "target_id": 19, "source": "Nami", "target": "Warwick", "win": 0.6296296296296297, "value": 54}, {"source_id": 143, "target_id": 222, "source": "Zyra", "target": "Jinx", "win": 0.6415094339622641, "value": 53}, {"source_id": 201, "target_id": 119, "source": "Braum", "target": "Draven", "win": 0.6792452830188679, "value": 53}, {"source_id": 54, "target_id": 51, "source": "Malphite", "target": "Caitlyn", "win": 0.6037735849056604, "value": 53}, {"source_id": 222, "target_id": 143, "source": "Jinx", "target": "Zyra", "win": 0.6415094339622641, "value": 53}, {"source_id": 91, "target_id": 59, "source": "Talon", "target": "JarvanIV", "win": 0.6037735849056604, "value": 53}, {"source_id": 75, "target_id": 90, "source": "Nasus", "target": "Malzahar", "win": 0.6415094339622641, "value": 53}, {"source_id": 51, "target_id": 54, "source": "Caitlyn", "target": "Malphite", "win": 0.6037735849056604, "value": 53}, {"source_id": 17, "target_id": 59, "source": "Teemo", "target": "JarvanIV", "win": 0.6415094339622641, "value": 53}, {"source_id": 27, "target_id": 117, "source": "Singed", "target": "Lulu", "win": 0.6226415094339622, "value": 53}, {"source_id": 117, "target_id": 27, "source": "Lulu", "target": "Singed", "win": 0.6226415094339622, "value": 53}, {"source_id": 119, "target_id": 201, "source": "Draven", "target": "Braum", "win": 0.6792452830188679, "value": 53}, {"source_id": 90, "target_id": 75, "source": "Malzahar", "target": "Nasus", "win": 0.6415094339622641, "value": 53}, {"source_id": 59, "target_id": 91, "source": "JarvanIV", "target": "Talon", "win": 0.6037735849056604, "value": 53}, {"source_id": 59, "target_id": 17, "source": "JarvanIV", "target": "Teemo", "win": 0.6415094339622641, "value": 53}, {"source_id": 498, "target_id": 33, "source": "Xayah", "target": "Rammus", "win": 0.6346153846153846, "value": 52}, {"source_id": 33, "target_id": 498, "source": "Rammus", "target": "Xayah", "win": 0.6346153846153846, "value": 52}, {"source_id": 21, "target_id": 432, "source": "MissFortune", "target": "Bard", "win": 0.6730769230769231, "value": 52}, {"source_id": 222, "target_id": 14, "source": "Jinx", "target": "Sion", "win": 0.6153846153846154, "value": 52}, {"source_id": 134, "target_id": 17, "source": "Syndra", "target": "Teemo", "win": 0.6346153846153846, "value": 52}, {"source_id": 107, "target_id": 89, "source": "Rengar", "target": "Leona", "win": 0.6538461538461539, "value": 52}, {"source_id": 98, "target_id": 89, "source": "Shen", "target": "Leona", "win": 0.6153846153846154, "value": 52}, {"source_id": 91, "target_id": 16, "source": "Talon", "target": "Soraka", "win": 0.6346153846153846, "value": 52}, {"source_id": 91, "target_id": 40, "source": "Talon", "target": "Janna", "win": 0.6730769230769231, "value": 52}, {"source_id": 432, "target_id": 21, "source": "Bard", "target": "MissFortune", "win": 0.6730769230769231, "value": 52}, {"source_id": 14, "target_id": 222, "source": "Sion", "target": "Jinx", "win": 0.6153846153846154, "value": 52}, {"source_id": 89, "target_id": 107, "source": "Leona", "target": "Rengar", "win": 0.6538461538461539, "value": 52}, {"source_id": 89, "target_id": 98, "source": "Leona", "target": "Shen", "win": 0.6153846153846154, "value": 52}, {"source_id": 17, "target_id": 134, "source": "Teemo", "target": "Syndra", "win": 0.6346153846153846, "value": 52}, {"source_id": 16, "target_id": 91, "source": "Soraka", "target": "Talon", "win": 0.6346153846153846, "value": 52}, {"source_id": 40, "target_id": 91, "source": "Janna", "target": "Talon", "win": 0.6730769230769231, "value": 52}, {"source_id": 42, "target_id": 18, "source": "Corki", "target": "Tristana", "win": 0.6862745098039216, "value": 51}, {"source_id": 201, "target_id": 75, "source": "Braum", "target": "Nasus", "win": 0.6078431372549019, "value": 51}, {"source_id": 21, "target_id": 131, "source": "MissFortune", "target": "Diana", "win": 0.6666666666666666, "value": 51}, {"source_id": 222, "target_id": 10, "source": "Jinx", "target": "Kayle", "win": 0.6078431372549019, "value": 51}, {"source_id": 10, "target_id": 222, "source": "Kayle", "target": "Jinx", "win": 0.6078431372549019, "value": 51}, {"source_id": 75, "target_id": 201, "source": "Nasus", "target": "Braum", "win": 0.6078431372549019, "value": 51}, {"source_id": 268, "target_id": 12, "source": "Azir", "target": "Alistar", "win": 0.6274509803921569, "value": 51}, {"source_id": 12, "target_id": 268, "source": "Alistar", "target": "Azir", "win": 0.6274509803921569, "value": 51}, {"source_id": 12, "target_id": 8, "source": "Alistar", "target": "Vladimir", "win": 0.6274509803921569, "value": 51}, {"source_id": 131, "target_id": 21, "source": "Diana", "target": "MissFortune", "win": 0.6666666666666666, "value": 51}, {"source_id": 18, "target_id": 42, "source": "Tristana", "target": "Corki", "win": 0.6862745098039216, "value": 51}, {"source_id": 8, "target_id": 12, "source": "Vladimir", "target": "Alistar", "win": 0.6274509803921569, "value": 51}]}